LICENSE
MANIFEST.in
README.rst
requirements-docs.txt
requirements-test.txt
requirements.txt
setup.cfg
setup.py
src/maidenhair/__init__.py
src/maidenhair/compat.py
src/maidenhair/functions.py
src/maidenhair.egg-info/PKG-INFO
src/maidenhair.egg-info/SOURCES.txt
src/maidenhair.egg-info/dependency_links.txt
src/maidenhair.egg-info/entry_points.txt
src/maidenhair.egg-info/requires.txt
src/maidenhair.egg-info/top_level.txt
src/maidenhair.egg-info/zip-safe
src/maidenhair/classification/__init__.py
src/maidenhair/classification/classify.py
src/maidenhair/classification/unite.py
src/maidenhair/filters/__init__.py
src/maidenhair/filters/baseline.py
src/maidenhair/filters/relative.py
src/maidenhair/loaders/__init__.py
src/maidenhair/loaders/base.py
src/maidenhair/loaders/plain.py
src/maidenhair/parsers/__init__.py
src/maidenhair/parsers/base.py
src/maidenhair/parsers/plain.py
src/maidenhair/statistics/__init__.py
src/maidenhair/utils/__init__.py
src/maidenhair/utils/environment.py
src/maidenhair/utils/peakset.py
src/maidenhair/utils/plugins.py
src/maidenhair/utils/rglob.py