Metadata-Version: 1.1
Name: maidenhair
Version: 0.3.3
Summary: Convert raw text data files into a single excel file.
Home-page: https://github.com/lambdalisue/maidenhair
Author: Alisue
Author-email: lambdalisue@hashnote.net
License: MIT
Download-URL: https://github.com/lambdalisue/maidenhair/tarball/master
Keywords: data python loader parser statistics
Platform: UNKNOWN
Classifier: Development Status :: 3 - Alpha
Classifier: Intended Audience :: Developers
Classifier: License :: OSI Approved :: MIT License
Classifier: Programming Language :: Python
Classifier: Programming Language :: Python :: 2.6
Classifier: Programming Language :: Python :: 2.7
